Metadata-Version: 1.0
Name: langlearn
Version: 1.0.1
Summary: Tool for practicing foreign language vocabulary and typing
Home-page: https://github.com/DevDungeon/LanguageLearner
Author: DevDungeon
Author-email: nanodano@devdungeon.com
License: GPL-3.0
Platform: UNKNOWN
